zaruti/trading.py
zaruti_trading-1.0.3.dist-info/METADATA
zaruti_trading-1.0.3.dist-info/RECORD
zaruti_trading-1.0.3.dist-info/WHEEL
zaruti_trading-1.0.3.dist-info/entry_points.txt
zaruti_trading-1.0.3.dist-info/top_level.txt
